elsa/__init__.py
elsa/elsa.py
elsarec-0.1.4.dist-info/LICENCE
elsarec-0.1.4.dist-info/METADATA
elsarec-0.1.4.dist-info/WHEEL
elsarec-0.1.4.dist-info/top_level.txt
elsarec-0.1.4.dist-info/RECORD
